changelogger/__init__.py
changelogger/__main__.py
changelogger/app/__init__.py
changelogger/app/commands/__init__.py
changelogger/app/commands/add.py
changelogger/app/commands/check.py
changelogger/app/commands/force.py
changelogger/app/commands/init.py
changelogger/app/commands/notes.py
changelogger/app/commands/precommit.py
changelogger/app/commands/upgrade.py
changelogger/app/commands/versions.py
changelogger/app/prompts.py
changelogger/changelog.py
changelogger/conf/__init__.py
changelogger/conf/defaults.py
changelogger/conf/git.py
changelogger/conf/models.py
changelogger/conf/settings.py
changelogger/exceptions.py
changelogger/models/__init__.py
changelogger/models/domain_models.py
changelogger/templates/changelog.md.jinja2
changelogger/templates/links.jinja2
changelogger/templates/overview.jinja2
changelogger/templates/release_notes.md.jinja2
changelogger/templating.py
changelogger/utils.py
changelogged-0.13.0.dist-info/METADATA
changelogged-0.13.0.dist-info/WHEEL
changelogged-0.13.0.dist-info/entry_points.txt
changelogged-0.13.0.dist-info/RECORD
