Metadata-Version: 2.1
Name: changelogged
Version: 0.13.0
Summary: Automated management of your changelog and other versioned files, following the principles of Keep a Changelog and Semantic Versioning.
Home-page: https://github.com/award28/changelogger
License: MIT
Keywords: changelog,version,semver,changelogger,changelogged
Author: award28
Author-email: austin.ward@klaviyo.com
Maintainer: award28
Maintainer-email: austin.ward@klaviyo.com
Requires-Python: >=3.10,<4.0
Classifier: License :: OSI Approved :: MIT License
Classifier: Programming Language :: Python :: 3
Classifier: Programming Language :: Python :: 3.10
Classifier: Programming Language :: Python :: 3.11
Requires-Dist: gitpython (==3.1.31)
Requires-Dist: jinja2 (==3.1.2)
Requires-Dist: pydantic (==1.10.6)
Requires-Dist: pyyaml (==6.0)
Requires-Dist: rich (==13.3.2)
Requires-Dist: semver (==2.13.0)
Requires-Dist: typer (==0.7.0)
Project-URL: Bug Tracker, https://github.com/award28/changelogger/issues
Project-URL: Changelog, https://github.com/award28/changelogger/blob/main/CHANGELOG.md
Project-URL: Repository, https://github.com/award28/changelogger
Project-URL: Road Map, https://github.com/users/award28/projects/2
